obfuslite/__init__.py
obfuslite/cli.py
obfuslite/core.py
obfuslite/gui.py
obfuslite/encoders/__init__.py
obfuslite/encoders/base.py
obfuslite/encoders/dna_encoder.py
obfuslite/encoders/fast_encoders.py
obfuslite/encoders/fractal_encoder.py
obfuslite/encoders/neural_encoder.py
obfuslite/encoders/quantum_encoder.py
obfuslite/encoders/runtime_reconstructor.py
obfuslite/encoders/simple_encoder.py
obfuslite/encoders/steganographic_encoder.py
obfuslite/encoders/tensor_encoder.py
obfuslite-1.1.0.dist-info/licenses/LICENSE
obfuslite-1.1.0.dist-info/METADATA
obfuslite-1.1.0.dist-info/WHEEL
obfuslite-1.1.0.dist-info/entry_points.txt
obfuslite-1.1.0.dist-info/top_level.txt
obfuslite-1.1.0.dist-info/RECORD
