Metadata-Version: 2.4
Name: obfuslite
Version: 1.1.0
Summary: Advanced Python code obfuscation library with enhanced GUI and multi-file support
Home-page: https://github.com/zinzied/obfuslite
Author: Zied Boughdir
Author-email: Zied Boughdir <zinzied@gmail.com>
License: MIT
Project-URL: Homepage, https://github.com/zinzied/obfuslite
Project-URL: Bug Reports, https://github.com/zinzied/obfuslite/issues
Project-URL: Source, https://github.com/zinzied/obfuslite
Project-URL: Documentation, https://github.com/zinzied/obfuslite/blob/main/README.md
Classifier: Development Status :: 5 - Production/Stable
Classifier: Intended Audience :: Developers
Classifier: Topic :: Software Development :: Libraries :: Python Modules
Classifier: Topic :: Security :: Cryptography
Classifier: License :: OSI Approved :: MIT License
Classifier: Programming Language :: Python :: 3
Classifier: Programming Language :: Python :: 3.8
Classifier: Programming Language :: Python :: 3.9
Classifier: Programming Language :: Python :: 3.10
Classifier: Programming Language :: Python :: 3.11
Classifier: Programming Language :: Python :: 3.12
Classifier: Operating System :: OS Independent
Requires-Python: >=3.8
License-File: LICENSE
Provides-Extra: gui
Requires-Dist: PyQt6>=6.4.0; extra == "gui"
Provides-Extra: dev
Requires-Dist: pytest>=7.0.0; extra == "dev"
Requires-Dist: pytest-cov>=4.0.0; extra == "dev"
Provides-Extra: full
Requires-Dist: PyQt6>=6.4.0; extra == "full"
Requires-Dist: numpy>=1.21.0; extra == "full"
Requires-Dist: scipy>=1.9.0; extra == "full"
Dynamic: author
Dynamic: home-page
Dynamic: license-file
Dynamic: requires-python
